{"inkVersion":20,"root":[["^Is anyone there?","\n","ev","str","^I'm here.","/str","/ev",{"*":"0.c-0","flg":20},{"c-0":["\n","^... We crashed... I'm the only one left. How do I get out of here?","\n",{"->":"0.g-0"},{"#f":5}],"g-0":["ev","str","^Can you describe where you are?","/str","/ev",{"*":".^.c-1","flg":20},{"c-1":["\n",{"->":"cave"},{"->":"0.g-1"},{"#f":5}],"#f":5}],"g-1":["done",{"#f":5}]}],"done",{"cave":[["^I'm ","ev",{"CNT?":"cave"},1,">","/ev",[{"->":".^.b","c":true},{"b":["^back",{"->":"cave.0.7"},null]}],"nop","^ in a cave.","\n",[["ev",{"^->":"cave.0.g-0.0.$r1"},{"temp=":"$r"},"str",{"->":".^.s"},[{"#n":"$r1"}],"/str","/ev",{"*":".^.^.c-0","flg":2},{"s":["^Go North",{"->":"$r","var":true},null]}],["ev",{"^->":"cave.0.g-0.1.$r1"},{"temp=":"$r"},"str",{"->":".^.s"},[{"#n":"$r1"}],"/str",{"CNT?":"valley"},"/ev",{"*":".^.^.c-1","flg":3},{"s":["^Go South",{"->":"$r","var":true},null]}],{"c-0":["ev",{"^->":"cave.0.g-0.c-0.$r2"},"/ev",{"temp=":"$r"},{"->":".^.^.0.s"},[{"#n":"$r2"}],"\n",{"->":"valley"},{"#f":5}],"c-1":["ev",{"^->":"cave.0.g-0.c-1.$r2"},"/ev",{"temp=":"$r"},{"->":".^.^.1.s"},[{"#n":"$r2"}],"\n","^Oh I found you!","\n","done",{"#f":5}],"#f":5,"#n":"g-0"}],null],{"#f":1}],"valley":[["^I'm in a valley","\n",["ev",{"^->":"valley.0.2.$r1"},{"temp=":"$r"},"str",{"->":".^.s"},[{"#n":"$r1"}],"/str","/ev",{"*":".^.^.c-0","flg":2},{"s":["^Go South",{"->":"$r","var":true},null]}],{"c-0":["ev",{"^->":"valley.0.c-0.$r2"},"/ev",{"temp=":"$r"},{"->":".^.^.2.s"},[{"#n":"$r2"}],"\n",{"->":"cave"},{"#f":5}]}],{"#f":1}],"#f":1}],"listDefs":{}}